enhanced_icm20948/__init__.py
enhanced_icm20948/__main__.py
enhanced_icm20948/asm_orientation.cpython-310-darwin.so
enhanced_icm20948/orientation.py
enhanced_icm20948-0.0.1.dist-info/LICENSE
enhanced_icm20948-0.0.1.dist-info/METADATA
enhanced_icm20948-0.0.1.dist-info/WHEEL
enhanced_icm20948-0.0.1.dist-info/top_level.txt
enhanced_icm20948-0.0.1.dist-info/RECORD
